automarkdown/__init__.py
automarkdown/automarkdown.py
automarkdown/cli.py
automarkdown/converter.py
automarkdown/parser.py
automarkdown/types.py
automarkdown-1.0.2.dist-info/licenses/LICENSE
automarkdown-1.0.2.dist-info/METADATA
automarkdown-1.0.2.dist-info/WHEEL
automarkdown-1.0.2.dist-info/entry_points.txt
automarkdown-1.0.2.dist-info/top_level.txt
automarkdown-1.0.2.dist-info/RECORD
