Metadata-Version: 2.4
Name: automarkdown
Version: 1.0.2
Summary: Intelligently convert codebases into markdown for LLMs to process and provide optimal insights
Home-page: https://github.com/harshpreet931/autoMarkdown
Author: harshpreet931
Author-email: 
Project-URL: Bug Reports, https://github.com/harshpreet931/autoMarkdown/issues
Project-URL: Source, https://github.com/harshpreet931/autoMarkdown
Project-URL: Documentation, https://github.com/harshpreet931/autoMarkdown#readme
Keywords: markdown codebase llm converter documentation automation
Classifier: Development Status :: 5 - Production/Stable
Classifier: Intended Audience :: Developers
Classifier: License :: OSI Approved :: MIT License
Classifier: Operating System :: OS Independent
Classifier: Programming Language :: Python :: 3
Classifier: Programming Language :: Python :: 3.7
Classifier: Programming Language :: Python :: 3.8
Classifier: Programming Language :: Python :: 3.9
Classifier: Programming Language :: Python :: 3.10
Classifier: Programming Language :: Python :: 3.11
Classifier: Topic :: Software Development :: Documentation
Classifier: Topic :: Text Processing :: Markup
Classifier: Topic :: Utilities
Requires-Python: >=3.7
License-File: LICENSE
Requires-Dist: click>=8.0.0
Requires-Dist: gitignore-parser>=0.1.0
Requires-Dist: colorama>=0.4.0
Dynamic: author
Dynamic: classifier
Dynamic: description
Dynamic: description-content-type
Dynamic: home-page
Dynamic: keywords
Dynamic: license-file
Dynamic: project-url
Dynamic: requires-dist
Dynamic: requires-python
Dynamic: summary
